aiidalab_widgets_empa/__init__.py
aiidalab_widgets_empa/cdxml.py
aiidalab_widgets_empa/computational_resources.py
aiidalab_widgets_empa/version.py
aiidalab_widgets_empa-0.2.2.dist-info/licenses/LICENSE
aiidalab_widgets_empa-0.2.2.dist-info/WHEEL
aiidalab_widgets_empa-0.2.2.dist-info/METADATA
aiidalab_widgets_empa-0.2.2.dist-info/RECORD
